mutablerecords-0.4.1.dist-info/top_level.txt
mutablerecords-0.4.1.dist-info/metadata.json
mutablerecords-0.4.1.dist-info/DESCRIPTION.rst
mutablerecords-0.4.1.dist-info/METADATA
mutablerecords-0.4.1.dist-info/RECORD
mutablerecords-0.4.1.dist-info/WHEEL
mutablerecords/records.py
mutablerecords/__init__.py
