Metadata-Version: 1.1
Name: mutablerecords
Version: 0.4.1
Summary: Mutable records
Home-page: https://github.com/chainreactionmfg/mutablerecords
Author: Fahrzin Hemmati
Author-email: fahhem@chainreactionmfg.com
License: Apache 2.0
Platform: UNKNOWN
Classifier: Development Status :: 4 - Beta
Classifier: Intended Audience :: Developers
Classifier: License :: OSI Approved :: Apache Software License
Classifier: Programming Language :: Python
Classifier: Programming Language :: Python :: 2
Classifier: Programming Language :: Python :: 3
Classifier: Topic :: Utilities
